server_pack/__init__.py
server_pack/common/__init__.py
server_pack/common/descriptor.py
server_pack/common/messages.py
server_pack/common/utils.py
server_pack/common/verifiers.py
server_pack/server/__init__.py
server_pack/server/multi_server.py
server_pack/server/repository.py
server_pack/server/server_utils.py
server_pack/server/utils.py
messenger_server_theksanacodes-0.0.1.dist-info/METADATA
messenger_server_theksanacodes-0.0.1.dist-info/WHEEL
messenger_server_theksanacodes-0.0.1.dist-info/top_level.txt
messenger_server_theksanacodes-0.0.1.dist-info/RECORD
